[{
        "id": 123,
        "Code": "kj133",
        "Name": "M1"
    },
    {
        "id": 124,
        "Code": "kj134",
        "Name": "M2"
    },
    {
        "id": 125,
        "Code": "kj135",
        "Name": "M3"
    },
    {
        "id": 126,
        "Code": "kj136",
        "Name": "M4"
    },
    {
        "id": 127,
        "Code": "kj137",
        "Name": "M5"
    },
    {
        "id": 128,
        "Code": "kj137",
        "Name": "M6"
    },
    {
        "id": 129,
        "Code": "kj137",
        "Name": "M7"
    },
    {
        "id": 130,
        "Code": "kj137",
        "Name": "M8"
    }
]